.DS_Store
dynamic_singer/__init__.py
dynamic_singer/function.py
dynamic_singer/helper.py
dynamic_singer/source.py
dynamic_singer/extra/__init__.py
dynamic_singer/extra/persistent.py
dynamic_singer/extra/postgres.py
dynamic_singer-0.0.20.dist-info/LICENSE
dynamic_singer-0.0.20.dist-info/METADATA
dynamic_singer-0.0.20.dist-info/WHEEL
dynamic_singer-0.0.20.dist-info/top_level.txt
dynamic_singer-0.0.20.dist-info/RECORD
